AUTHORS
ChangeLog
LICENSE
MANIFEST.in
README.rst
requirements.txt
setup.cfg
setup.py
bsnlldp/__init__.py
bsnlldp/bsnlldp.py
bsnlldp.egg-info/PKG-INFO
bsnlldp.egg-info/SOURCES.txt
bsnlldp.egg-info/dependency_links.txt
bsnlldp.egg-info/entry_points.txt
bsnlldp.egg-info/not-zip-safe
bsnlldp.egg-info/pbr.json
bsnlldp.egg-info/requires.txt
bsnlldp.egg-info/top_level.txt
etc/bsnlldp.service
etc/python-networking-bigswitch-bsnlldp.spec